to_upload/__init__.py
to_upload/clases.py
andre_blaze-0.1.0.dist-info/METADATA
andre_blaze-0.1.0.dist-info/WHEEL
andre_blaze-0.1.0.dist-info/top_level.txt
andre_blaze-0.1.0.dist-info/RECORD
